sflvault/__init__.py
sflvault/clientqt/__init__.py
sflvault/clientqt/gui/__init__.py
sflvault/clientqt/gui/mainWindow.py
sflvault/clientqt/gui/bar/__init__.py
sflvault/clientqt/gui/bar/filterbar.py
sflvault/clientqt/gui/bar/menubar.py
sflvault/clientqt/gui/bar/osd.py
sflvault/clientqt/gui/bar/systray.py
sflvault/clientqt/gui/config/__init__.py
sflvault/clientqt/gui/config/config.py
sflvault/clientqt/gui/config/customer.py
sflvault/clientqt/gui/config/machine.py
sflvault/clientqt/gui/config/preferences.py
sflvault/clientqt/gui/config/protocols.py
sflvault/clientqt/gui/config/service.py
sflvault/clientqt/gui/config/users.py
sflvault/clientqt/gui/dialog/__init__.py
sflvault/clientqt/gui/dialog/aboutdialog.py
sflvault/clientqt/gui/dialog/progressdialog.py
sflvault/clientqt/gui/dialog/webpreview.py
sflvault/clientqt/gui/docks/__init__.py
sflvault/clientqt/gui/docks/aliasdock.py
sflvault/clientqt/gui/docks/infodock.py
sflvault/clientqt/gui/docks/searchdock.py
sflvault/clientqt/gui/tree/__init__.py
sflvault/clientqt/gui/tree/tree.py
sflvault/clientqt/gui/wizard/__init__.py
sflvault/clientqt/gui/wizard/initaccount.py
sflvault/clientqt/gui/wizard/savepassword.py
sflvault/clientqt/i18n/sflvault-qt4_en.qm
sflvault/clientqt/i18n/sflvault-qt4_fr.qm
sflvault/clientqt/images/__init__.py
sflvault/clientqt/images/add.png
sflvault/clientqt/images/alias.png
sflvault/clientqt/images/close.png
sflvault/clientqt/images/computer.png
sflvault/clientqt/images/configure.png
sflvault/clientqt/images/connect.png
sflvault/clientqt/images/critical.png
sflvault/clientqt/images/customer.png
sflvault/clientqt/images/disconnect.png
sflvault/clientqt/images/exit.png
sflvault/clientqt/images/filter.png
sflvault/clientqt/images/find.png
sflvault/clientqt/images/group.png
sflvault/clientqt/images/information.png
sflvault/clientqt/images/internet.png
sflvault/clientqt/images/machine.png
sflvault/clientqt/images/network.png
sflvault/clientqt/images/notes.png
sflvault/clientqt/images/password.png
SFLvault_client_qt-0.9.2.dist-info/LICENSE
SFLvault_client_qt-0.9.2.dist-info/METADATA
SFLvault_client_qt-0.9.2.dist-info/WHEEL
SFLvault_client_qt-0.9.2.dist-info/entry_points.txt
SFLvault_client_qt-0.9.2.dist-info/top_level.txt
SFLvault_client_qt-0.9.2.dist-info/RECORD
