Metadata-Version: 2.1
Name: SFLvault-client-qt
Version: 0.9.2
Summary: Networked credentials store and authentication manager - Qt Client
Home-page: https://www.sflvault.org
Author: Savoir-faire Linux
Author-email: contact@savoirfairelinux.com
License: GPLv2
Platform: UNKNOWN
Requires-Dist: SFLvault-client (~=0.9)
Requires-Dist: SFLvault-common (~=0.9)
